{"is_source_file": true, "format": "JavaScript", "description": "Setup file for testing environment using Jest and React Testing Library, importing custom DOM matchers from '@testing-library/jest-dom'.", "external_files": ["@testing-library/jest-dom"], "external_methods": [], "published": [], "classes": [], "methods": [], "calls": ["import '@testing-library/jest-dom'"], "search-terms": ["setupTests.js", "jest-dom", "testing environment", "React Testing Library"], "state": 2, "file_id": 6, "knowledge_revision": 23, "git_revision": "c070a2a9200fde8c7d5e24c2933a1caf3fbb58f4", "ctags": [], "hash": "1a77571e1a8cf36018a41bcedf60db75", "format-version": 4, "code-base-name": "frontend_app", "filename": "frontend_app/src/setupTests.js", "revision_history": [{"23": "c070a2a9200fde8c7d5e24c2933a1caf3fbb58f4"}]}